tju/__init__.py
tju-0.0.1.dist-info/METADATA
tju-0.0.1.dist-info/WHEEL
tju-0.0.1.dist-info/top_level.txt
tju-0.0.1.dist-info/RECORD
