Metadata-Version: 2.1
Name: tju
Version: 0.0.1
Summary: The Python TJU client for humans.
Home-page: https://github.com/superpung/tju
Author: super
Author-email: hi@repus.me
